setup.py
finacc/__init__.py
finacc/banking.py
finacc/general.py
finacc/investment.py
python_finacc.egg-info/PKG-INFO
python_finacc.egg-info/SOURCES.txt
python_finacc.egg-info/dependency_links.txt
python_finacc.egg-info/not-zip-safe
python_finacc.egg-info/top_level.txt