Metadata-Version: 1.0
Name: python-finacc
Version: 0.1.alpha
Summary: A financial calculation library for python
Home-page: https://github.com/samithdisal/python-finacc
Author: Samith Sandanayake
Author-email: samithdisal@gmail.com
License: MIT
Platform: UNKNOWN
